<?xml version="1.0" encoding="UTF-8"?>
<list xmlns:xsi="http://www.w3.org/2001/XMLSchema-instance" xsi:noNamespaceSchemaLocation="../../../xsd/optionsData.xsd">
	<option id="10700" name="o_f_67_2u_53">
		<!-- Max HP increases by 16.84. Evasion increases by 0.87. -->
		<for>
			<add stat="maxMp" val="16.842" />
			<add stat="rEvas" val="0.874901" />
		</for>
	</option>
	<option id="10701" name="o_f_67_2u_54">
		<!-- Max HP increases by 16.84. Accuracy increases by 0.87. -->
		<for>
			<add stat="maxMp" val="16.842" />
			<add stat="accCombat" val="0.874901" />
		</for>
	</option>
	<option id="10702" name="o_f_67_2u_55">
		<!-- Max HP increases by 16.84. Critical increases by 9.47. -->
		<for>
			<add stat="maxMp" val="16.842" />
			<add stat="critRate" val="9.473428028" />
		</for>
	</option>
	<option id="10703" name="o_f_67_2u_56">
		<!-- Max CP increases by 71.92. P. Atk. increases by 7.05. -->
		<for>
			<add stat="maxCp" val="71.9222" />
			<add stat="pAtk" val="7.046" />
		</for>
	</option>
	<option id="10704" name="o_f_67_2u_57">
		<!-- Max CP increases by 71.92. M. Atk. increases by 8.26. -->
		<for>
			<add stat="maxCp" val="71.9222" />
			<add stat="mAtk" val="8.255" />
		</for>
	</option>
	<option id="10705" name="o_f_67_2u_58">
		<!-- Max CP increases by 71.92. HP Regen increases by 0.24. -->
		<for>
			<add stat="maxCp" val="71.9222" />
			<add stat="regHp" val="0.23946" />
		</for>
	</option>
	<option id="10706" name="o_f_67_2u_59">
		<!-- Max CP increases by 71.92. MP Regen increases by 0.11. -->
		<for>
			<add stat="maxCp" val="71.9222" />
			<add stat="regMp" val="0.1053" />
		</for>
	</option>
	<option id="10707" name="o_f_67_2u_60">
		<!-- Max CP increases by 71.92. CP Regen increases by 0.24. -->
		<for>
			<add stat="maxCp" val="71.9222" />
			<add stat="regCp" val="0.23946" />
		</for>
	</option>
	<option id="10708" name="o_f_67_2u_61">
		<!-- Max CP increases by 71.92. Evasion increases by 0.87. -->
		<for>
			<add stat="maxCp" val="71.9222" />
			<add stat="rEvas" val="0.874901" />
		</for>
	</option>
	<option id="10709" name="o_f_67_2u_62">
		<!-- Max CP increases by 71.92. Accuracy increases by 0.87. -->
		<for>
			<add stat="maxCp" val="71.9222" />
			<add stat="accCombat" val="0.874901" />
		</for>
	</option>
	<option id="10710" name="o_f_67_2u_63">
		<!-- Max CP increases by 71.92. Critical increases by 9.47. -->
		<for>
			<add stat="maxCp" val="71.9222" />
			<add stat="critRate" val="9.473428028" />
		</for>
	</option>
	<option id="10711" name="o_f_67_2u_64">
		<!-- P. Atk. increases by 7.59. M. Atk. increases by 8.26. -->
		<for>
			<add stat="pAtk" val="7.588" />
			<add stat="mAtk" val="8.255" />
		</for>
	</option>
	<option id="10712" name="o_f_67_2u_65">
		<!-- P. Atk. increases by 7.59. HP Regen increases by 0.24. -->
		<for>
			<add stat="pAtk" val="7.588" />
			<add stat="regHp" val="0.23946" />
		</for>
	</option>
	<option id="10713" name="o_f_67_2u_66">
		<!-- P. Atk. increases by 7.59. MP Regen increases by 0.11. -->
		<for>
			<add stat="pAtk" val="7.588" />
			<add stat="regMp" val="0.1053" />
		</for>
	</option>
	<option id="10714" name="o_f_67_2u_67">
		<!-- P. Atk. increases by 7.59. CP Regen increases by 0.24. -->
		<for>
			<add stat="pAtk" val="7.588" />
			<add stat="regCp" val="0.23946" />
		</for>
	</option>
	<option id="10715" name="o_f_67_2u_68">
		<!-- P. Atk. increases by 7.59. Evasion increases by 0.87. -->
		<for>
			<add stat="pAtk" val="7.588" />
			<add stat="rEvas" val="0.874901" />
		</for>
	</option>
	<option id="10716" name="o_f_67_2u_69">
		<!-- P. Atk. increases by 7.59. Accuracy increases by 0.87. -->
		<for>
			<add stat="pAtk" val="7.588" />
			<add stat="accCombat" val="0.874901" />
		</for>
	</option>
	<option id="10717" name="o_f_67_2u_70">
		<!-- P. Atk. increases by 7.59. Critical increases by 9.47. -->
		<for>
			<add stat="pAtk" val="7.588" />
			<add stat="critRate" val="9.473428028" />
		</for>
	</option>
	<option id="10718" name="o_f_67_2u_71">
		<!-- M. Atk. increases by 8.89. HP Regen increases by 0.24. -->
		<for>
			<add stat="mAtk" val="8.89" />
			<add stat="regHp" val="0.23946" />
		</for>
	</option>
	<option id="10719" name="o_f_67_2u_72">
		<!-- M. Atk. increases by 8.89. MP Regen increases by 0.11. -->
		<for>
			<add stat="mAtk" val="8.89" />
			<add stat="regMp" val="0.1053" />
		</for>
	</option>
	<option id="10720" name="o_f_67_2u_73">
		<!-- M. Atk. increases by 8.89. CP Regen increases by 0.24. -->
		<for>
			<add stat="mAtk" val="8.89" />
			<add stat="regCp" val="0.23946" />
		</for>
	</option>
	<option id="10721" name="o_f_67_2u_74">
		<!-- M. Atk. increases by 8.89. Evasion increases by 0.87. -->
		<for>
			<add stat="mAtk" val="8.89" />
			<add stat="rEvas" val="0.874901" />
		</for>
	</option>
	<option id="10722" name="o_f_67_2u_75">
		<!-- M. Atk. increases by 8.89. Accuracy increases by 0.87. -->
		<for>
			<add stat="mAtk" val="8.89" />
			<add stat="accCombat" val="0.874901" />
		</for>
	</option>
	<option id="10723" name="o_f_67_2u_76">
		<!-- M. Atk. increases by 8.89. Critical increases by 9.47. -->
		<for>
			<add stat="mAtk" val="8.89" />
			<add stat="critRate" val="9.473428028" />
		</for>
	</option>
	<option id="10724" name="o_f_67_2u_77">
		<!-- HP Regen increases by 0.26. MP Regen increases by 0.11. -->
		<for>
			<add stat="regHp" val="0.25788" />
			<add stat="regMp" val="0.1053" />
		</for>
	</option>
	<option id="10725" name="o_f_67_2u_78">
		<!-- HP Regen increases by 0.26. CP Regen increases by 0.24. -->
		<for>
			<add stat="regHp" val="0.25788" />
			<add stat="regCp" val="0.23946" />
		</for>
	</option>
	<option id="10726" name="o_f_67_2u_79">
		<!-- HP Regen increases by 0.26. Evasion increases by 0.87. -->
		<for>
			<add stat="regHp" val="0.25788" />
			<add stat="rEvas" val="0.874901" />
		</for>
	</option>
	<option id="10727" name="o_f_67_2u_80">
		<!-- HP Regen increases by 0.26. Accuracy increases by 0.87. -->
		<for>
			<add stat="regHp" val="0.25788" />
			<add stat="accCombat" val="0.874901" />
		</for>
	</option>
	<option id="10728" name="o_f_67_2u_81">
		<!-- HP Regen increases by 0.26. Critical increases by 9.47. -->
		<for>
			<add stat="regHp" val="0.25788" />
			<add stat="critRate" val="9.473428028" />
		</for>
	</option>
	<option id="10729" name="o_f_67_2u_82">
		<!-- MP Regen increases by 0.11. CP Regen increases by 0.24. -->
		<for>
			<add stat="regMp" val="0.1134" />
			<add stat="regCp" val="0.23946" />
		</for>
	</option>
	<option id="10730" name="o_f_67_2u_83">
		<!-- MP Regen increases by 0.11. Evasion increases by 0.87. -->
		<for>
			<add stat="regMp" val="0.1134" />
			<add stat="rEvas" val="0.874901" />
		</for>
	</option>
	<option id="10731" name="o_f_67_2u_84">
		<!-- MP Regen increases by 0.11. Accuracy increases by 0.87. -->
		<for>
			<add stat="regMp" val="0.1134" />
			<add stat="accCombat" val="0.874901" />
		</for>
	</option>
	<option id="10732" name="o_f_67_2u_85">
		<!-- MP Regen increases by 0.11. Critical increases by 9.47. -->
		<for>
			<add stat="regMp" val="0.1134" />
			<add stat="critRate" val="9.473428028" />
		</for>
	</option>
	<option id="10733" name="o_f_67_2u_86">
		<!-- CP Regen increases by 0.26. Evasion increases by 0.87. -->
		<for>
			<add stat="regCp" val="0.25788" />
			<add stat="rEvas" val="0.874901" />
		</for>
	</option>
	<option id="10734" name="o_f_67_2u_87">
		<!-- CP Regen increases by 0.26. Accuracy increases by 0.87. -->
		<for>
			<add stat="regCp" val="0.25788" />
			<add stat="accCombat" val="0.874901" />
		</for>
	</option>
	<option id="10735" name="o_f_67_2u_88">
		<!-- CP Regen increases by 0.26. Critical increases by 9.47. -->
		<for>
			<add stat="regCp" val="0.25788" />
			<add stat="critRate" val="9.473428028" />
		</for>
	</option>
	<option id="10736" name="o_f_67_2u_89">
		<!-- Evasion increases by 0.97. Accuracy increases by 0.87. -->
		<for>
			<add stat="rEvas" val="0.966995" />
			<add stat="accCombat" val="0.874901" />
		</for>
	</option>
	<option id="10737" name="o_f_67_2u_90">
		<!-- Evasion increases by 0.97. Critical increases by 9.47. -->
		<for>
			<add stat="rEvas" val="0.966995" />
			<add stat="critRate" val="9.473428028" />
		</for>
	</option>
	<option id="10738" name="o_f_67_2u_91">
		<!-- Accuracy increases by 0.97. Critical increases by 9.47. -->
		<for>
			<add stat="accCombat" val="0.966995" />
			<add stat="critRate" val="9.473428028" />
		</for>
	</option>
	<option id="10739" name="o_f_70_2u_1">
		<!-- P. Def. increases by 24.63. -->
		<for>
			<add stat="pDef" val="24.625" />
		</for>
	</option>
	<option id="10740" name="o_f_70_2u_2">
		<!-- M. Def. increases by 19.8. -->
		<for>
			<add stat="mDef" val="19.8" />
		</for>
	</option>
	<option id="10741" name="o_f_70_2u_3">
		<!-- Max HP increases by 99.73 -->
		<for>
			<add stat="maxHp" val="99.725" />
		</for>
	</option>
	<option id="10742" name="o_f_70_2u_4">
		<!-- Max HP increases by 32.38. -->
		<for>
			<add stat="maxMp" val="32.375" />
		</for>
	</option>
	<option id="10743" name="o_f_70_2u_5">
		<!-- Max CP increases by 137.72. -->
		<for>
			<add stat="maxCp" val="137.7175" />
		</for>
	</option>
	<option id="10744" name="o_f_70_2u_6">
		<!-- P. Atk. increases by 15.1. -->
		<for>
			<add stat="pAtk" val="15.1" />
		</for>
	</option>
	<option id="10745" name="o_f_70_2u_7">
		<!-- M. Atk. increases by 17.5. -->
		<for>
			<add stat="mAtk" val="17.5" />
		</for>
	</option>
	<option id="10746" name="o_f_70_2u_8">
		<!-- HP Regen increases by 0.47. -->
		<for>
			<add stat="regHp" val="0.4695" />
		</for>
	</option>
	<option id="10747" name="o_f_70_2u_9">
		<!-- MP Regen increases by 0.21. -->
		<for>
			<add stat="regMp" val="0.205" />
		</for>
	</option>
	<option id="10748" name="o_f_70_2u_10">
		<!-- CP Regen increases by 0.47. -->
		<for>
			<add stat="regCp" val="0.4695" />
		</for>
	</option>
	<option id="10749" name="o_f_70_2u_11">
		<!-- Evasion increases by 1.84. -->
		<for>
			<add stat="rEvas" val="1.841896" />
		</for>
	</option>
	<option id="10750" name="o_f_70_2u_12">
		<!-- Accuracy increases by 1.84. -->
		<for>
			<add stat="accCombat" val="1.841896" />
		</for>
	</option>
	<option id="10751" name="o_f_70_2u_13">
		<!-- Critical increases by 19.94. -->
		<for>
			<add stat="critRate" val="19.944049888" />
		</for>
	</option>
	<option id="10752" name="o_f_70_2u_14">
		<!-- P. Def. increases by 12.81. M. Def. increases by 9.5. -->
		<for>
			<add stat="pDef" val="12.805" />
			<add stat="mDef" val="9.504" />
		</for>
	</option>
	<option id="10753" name="o_f_70_2u_15">
		<!-- P. Def. increases by 12.81. Max HP increases by 47.87 -->
		<for>
			<add stat="pDef" val="12.805" />
			<add stat="maxHp" val="47.868" />
		</for>
	</option>
	<option id="10754" name="o_f_70_2u_16">
		<!-- P. Def. increases by 12.81. Max HP increases by 15.54. -->
		<for>
			<add stat="pDef" val="12.805" />
			<add stat="maxMp" val="15.54" />
		</for>
	</option>
	<option id="10755" name="o_f_70_2u_17">
		<!-- P. Def. increases by 12.81. Max CP increases by 66.1. -->
		<for>
			<add stat="pDef" val="12.805" />
			<add stat="maxCp" val="66.1044" />
		</for>
	</option>
	<option id="10756" name="o_f_70_2u_18">
		<!-- P. Def. increases by 12.81. P. Atk. increases by 7.25. -->
		<for>
			<add stat="pDef" val="12.805" />
			<add stat="pAtk" val="7.248" />
		</for>
	</option>
	<option id="10757" name="o_f_70_2u_19">
		<!-- P. Def. increases by 12.81. M. Atk. increases by 8.4. -->
		<for>
			<add stat="pDef" val="12.805" />
			<add stat="mAtk" val="8.4" />
		</for>
	</option>
	<option id="10758" name="o_f_70_2u_20">
		<!-- P. Def. increases by 12.81. HP Regen increases by 0.23. -->
		<for>
			<add stat="pDef" val="12.805" />
			<add stat="regHp" val="0.22536" />
		</for>
	</option>
	<option id="10759" name="o_f_70_2u_21">
		<!-- P. Def. increases by 12.81. MP Regen increases by 0.1. -->
		<for>
			<add stat="pDef" val="12.805" />
			<add stat="regMp" val="0.0984" />
		</for>
	</option>
	<option id="10760" name="o_f_70_2u_22">
		<!-- P. Def. increases by 12.81. CP Regen increases by 0.23. -->
		<for>
			<add stat="pDef" val="12.805" />
			<add stat="regCp" val="0.22536" />
		</for>
	</option>
	<option id="10761" name="o_f_70_2u_23">
		<!-- P. Def. increases by 12.81. Evasion increases by 0.87. -->
		<for>
			<add stat="pDef" val="12.805" />
			<add stat="rEvas" val="0.874901" />
		</for>
	</option>
	<option id="10762" name="o_f_70_2u_24">
		<!-- P. Def. increases by 12.81. Accuracy increases by 0.87. -->
		<for>
			<add stat="pDef" val="12.805" />
			<add stat="accCombat" val="0.874901" />
		</for>
	</option>
	<option id="10763" name="o_f_70_2u_25">
		<!-- P. Def. increases by 12.81. Critical increases by 9.47. -->
		<for>
			<add stat="pDef" val="12.805" />
			<add stat="critRate" val="9.473428028" />
		</for>
	</option>
	<option id="10764" name="o_f_70_2u_26">
		<!-- M. Def. increases by 10.3. Max HP increases by 47.87 -->
		<for>
			<add stat="mDef" val="10.296" />
			<add stat="maxHp" val="47.868" />
		</for>
	</option>
	<option id="10765" name="o_f_70_2u_27">
		<!-- M. Def. increases by 10.3. Max HP increases by 15.54. -->
		<for>
			<add stat="mDef" val="10.296" />
			<add stat="maxMp" val="15.54" />
		</for>
	</option>
	<option id="10766" name="o_f_70_2u_28">
		<!-- M. Def. increases by 10.3. Max CP increases by 66.1. -->
		<for>
			<add stat="mDef" val="10.296" />
			<add stat="maxCp" val="66.1044" />
		</for>
	</option>
	<option id="10767" name="o_f_70_2u_29">
		<!-- M. Def. increases by 10.3. P. Atk. increases by 7.25. -->
		<for>
			<add stat="mDef" val="10.296" />
			<add stat="pAtk" val="7.248" />
		</for>
	</option>
	<option id="10768" name="o_f_70_2u_30">
		<!-- M. Def. increases by 10.3. M. Atk. increases by 8.4. -->
		<for>
			<add stat="mDef" val="10.296" />
			<add stat="mAtk" val="8.4" />
		</for>
	</option>
	<option id="10769" name="o_f_70_2u_31">
		<!-- M. Def. increases by 10.3. HP Regen increases by 0.23. -->
		<for>
			<add stat="mDef" val="10.296" />
			<add stat="regHp" val="0.22536" />
		</for>
	</option>
	<option id="10770" name="o_f_70_2u_32">
		<!-- M. Def. increases by 10.3. MP Regen increases by 0.1. -->
		<for>
			<add stat="mDef" val="10.296" />
			<add stat="regMp" val="0.0984" />
		</for>
	</option>
	<option id="10771" name="o_f_70_2u_33">
		<!-- M. Def. increases by 10.3. CP Regen increases by 0.23. -->
		<for>
			<add stat="mDef" val="10.296" />
			<add stat="regCp" val="0.22536" />
		</for>
	</option>
	<option id="10772" name="o_f_70_2u_34">
		<!-- M. Def. increases by 10.3. Evasion increases by 0.87. -->
		<for>
			<add stat="mDef" val="10.296" />
			<add stat="rEvas" val="0.874901" />
		</for>
	</option>
	<option id="10773" name="o_f_70_2u_35">
		<!-- M. Def. increases by 10.3. Accuracy increases by 0.87. -->
		<for>
			<add stat="mDef" val="10.296" />
			<add stat="accCombat" val="0.874901" />
		</for>
	</option>
	<option id="10774" name="o_f_70_2u_36">
		<!-- M. Def. increases by 10.3. Critical increases by 9.47. -->
		<for>
			<add stat="mDef" val="10.296" />
			<add stat="critRate" val="9.473428028" />
		</for>
	</option>
	<option id="10775" name="o_f_70_2u_37">
		<!-- Max HP increases by 51.86 Max HP increases by 15.54. -->
		<for>
			<add stat="maxHp" val="51.857" />
			<add stat="maxMp" val="15.54" />
		</for>
	</option>
	<option id="10776" name="o_f_70_2u_38">
		<!-- Max HP increases by 51.86 Max CP increases by 66.1. -->
		<for>
			<add stat="maxHp" val="51.857" />
			<add stat="maxCp" val="66.1044" />
		</for>
	</option>
	<option id="10777" name="o_f_70_2u_39">
		<!-- Max HP increases by 51.86 P. Atk. increases by 7.25. -->
		<for>
			<add stat="maxHp" val="51.857" />
			<add stat="pAtk" val="7.248" />
		</for>
	</option>
	<option id="10778" name="o_f_70_2u_40">
		<!-- Max HP increases by 51.86 M. Atk. increases by 8.4. -->
		<for>
			<add stat="maxHp" val="51.857" />
			<add stat="mAtk" val="8.4" />
		</for>
	</option>
	<option id="10779" name="o_f_70_2u_41">
		<!-- Max HP increases by 51.86 HP Regen increases by 0.23. -->
		<for>
			<add stat="maxHp" val="51.857" />
			<add stat="regHp" val="0.22536" />
		</for>
	</option>
	<option id="10780" name="o_f_70_2u_42">
		<!-- Max HP increases by 51.86 MP Regen increases by 0.1. -->
		<for>
			<add stat="maxHp" val="51.857" />
			<add stat="regMp" val="0.0984" />
		</for>
	</option>
	<option id="10781" name="o_f_70_2u_43">
		<!-- Max HP increases by 51.86 CP Regen increases by 0.23. -->
		<for>
			<add stat="maxHp" val="51.857" />
			<add stat="regCp" val="0.22536" />
		</for>
	</option>
	<option id="10782" name="o_f_70_2u_44">
		<!-- Max HP increases by 51.86 Evasion increases by 0.87. -->
		<for>
			<add stat="maxHp" val="51.857" />
			<add stat="rEvas" val="0.874901" />
		</for>
	</option>
	<option id="10783" name="o_f_70_2u_45">
		<!-- Max HP increases by 51.86 Accuracy increases by 0.87. -->
		<for>
			<add stat="maxHp" val="51.857" />
			<add stat="accCombat" val="0.874901" />
		</for>
	</option>
	<option id="10784" name="o_f_70_2u_46">
		<!-- Max HP increases by 51.86 Critical increases by 9.47. -->
		<for>
			<add stat="maxHp" val="51.857" />
			<add stat="critRate" val="9.473428028" />
		</for>
	</option>
	<option id="10785" name="o_f_70_2u_47">
		<!-- Max HP increases by 16.84. Max CP increases by 66.1. -->
		<for>
			<add stat="maxMp" val="16.835" />
			<add stat="maxCp" val="66.1044" />
		</for>
	</option>
	<option id="10786" name="o_f_70_2u_48">
		<!-- Max HP increases by 16.84. P. Atk. increases by 7.25. -->
		<for>
			<add stat="maxMp" val="16.835" />
			<add stat="pAtk" val="7.248" />
		</for>
	</option>
	<option id="10787" name="o_f_70_2u_49">
		<!-- Max HP increases by 16.84. M. Atk. increases by 8.4. -->
		<for>
			<add stat="maxMp" val="16.835" />
			<add stat="mAtk" val="8.4" />
		</for>
	</option>
	<option id="10788" name="o_f_70_2u_50">
		<!-- Max HP increases by 16.84. HP Regen increases by 0.23. -->
		<for>
			<add stat="maxMp" val="16.835" />
			<add stat="regHp" val="0.22536" />
		</for>
	</option>
	<option id="10789" name="o_f_70_2u_51">
		<!-- Max HP increases by 16.84. MP Regen increases by 0.1. -->
		<for>
			<add stat="maxMp" val="16.835" />
			<add stat="regMp" val="0.0984" />
		</for>
	</option>
	<option id="10790" name="o_f_70_2u_52">
		<!-- Max HP increases by 16.84. CP Regen increases by 0.23. -->
		<for>
			<add stat="maxMp" val="16.835" />
			<add stat="regCp" val="0.22536" />
		</for>
	</option>
	<option id="10791" name="o_f_70_2u_53">
		<!-- Max HP increases by 16.84. Evasion increases by 0.87. -->
		<for>
			<add stat="maxMp" val="16.835" />
			<add stat="rEvas" val="0.874901" />
		</for>
	</option>
	<option id="10792" name="o_f_70_2u_54">
		<!-- Max HP increases by 16.84. Accuracy increases by 0.87. -->
		<for>
			<add stat="maxMp" val="16.835" />
			<add stat="accCombat" val="0.874901" />
		</for>
	</option>
	<option id="10793" name="o_f_70_2u_55">
		<!-- Max HP increases by 16.84. Critical increases by 9.47. -->
		<for>
			<add stat="maxMp" val="16.835" />
			<add stat="critRate" val="9.473428028" />
		</for>
	</option>
	<option id="10794" name="o_f_70_2u_56">
		<!-- Max CP increases by 71.61. P. Atk. increases by 7.25. -->
		<for>
			<add stat="maxCp" val="71.6131" />
			<add stat="pAtk" val="7.248" />
		</for>
	</option>
	<option id="10795" name="o_f_70_2u_57">
		<!-- Max CP increases by 71.61. M. Atk. increases by 8.4. -->
		<for>
			<add stat="maxCp" val="71.6131" />
			<add stat="mAtk" val="8.4" />
		</for>
	</option>
	<option id="10796" name="o_f_70_2u_58">
		<!-- Max CP increases by 71.61. HP Regen increases by 0.23. -->
		<for>
			<add stat="maxCp" val="71.6131" />
			<add stat="regHp" val="0.22536" />
		</for>
	</option>
	<option id="10797" name="o_f_70_2u_59">
		<!-- Max CP increases by 71.61. MP Regen increases by 0.1. -->
		<for>
			<add stat="maxCp" val="71.6131" />
			<add stat="regMp" val="0.0984" />
		</for>
	</option>
	<option id="10798" name="o_f_70_2u_60">
		<!-- Max CP increases by 71.61. CP Regen increases by 0.23. -->
		<for>
			<add stat="maxCp" val="71.6131" />
			<add stat="regCp" val="0.22536" />
		</for>
	</option>
	<option id="10799" name="o_f_70_2u_61">
		<!-- Max CP increases by 71.61. Evasion increases by 0.87. -->
		<for>
			<add stat="maxCp" val="71.6131" />
			<add stat="rEvas" val="0.874901" />
		</for>
	</option>
</list>